atopy/__init__.py
atopy/datetime.py
atopy/decimal.py
atopy/io.py
atopy/main.py
atopy/py.typed
atopy/pydantic.py
atopy/typer.py
atopy-1.0.0.dist-info/LICENSE
atopy-1.0.0.dist-info/WHEEL
atopy-1.0.0.dist-info/METADATA
atopy-1.0.0.dist-info/RECORD
